Workbook

Sheet PEDIDO COMERCIAL
A1: REDE MEGA 12 • PLANILHA MODELO DE IMPORTAÇÃO DE PEDIDOS | I1: MODELO OFICIAL V2.0
A2: ALS 10 BAZAR E BRINQUEDOS LTDA • ESTRUTURA INTELIGENTE ANTI-ERRO | I2: Uso: Compras e Fornecedores
A3: ℹ️ INSTRUÇÕES: Preencha os Dados do Fornecedor, Condições e Produtos. A coluna TOTAL PEÇAS calcula automaticamente (= QTD/CX × QTD CX).
A5: 1. DADOS DA EMPRESA COMPRADORA (DESTINATÁRIO - MEGA 12): | F5: 2. DADOS DO FORNECEDOR & VENDEDOR (PREENCHA SEUS DADOS):
A6: Razão Social: | B6: ALS 10 BAZAR E BRINQUEDOS LTDA | F6: Razão Social: | G6: FORNECEDOR EXEMPLO BRASIL LTDA
A7: CNPJ / IE: | B7: 37.144.240/0001-70 IE: 90847822-35 | F7: CNPJ: | G7: 12.345.678/0001-90
A8: End. Entrega: | B8: Av. José Galiciolli, 152 – BR153 – Centro – Irati – PR (CEP: 84500-009) | F8: Vendedor: | G8: Carlos Eduardo
A9: Boletos / XML: | B9: als.conecta@gmail.com | F9: WhatsApp / Fone: | G9: (41) 99888-7766
A10: Compras: | B10: Rafael (55) 9 9659-6315 | Bruna (55) 9 3618-5609 | F10: E-mail Vendas: | G10: vendas@fornecedorexemplo.com.br
A12: 3. CONDIÇÕES COMERCIAIS, PRAZOS & FRETE:
A13: Nº Pedido: | B13: PED-FORNEC-001 | C13: Data Pedido: | D13: 14/09/2026 | E13: Entrega: | F13: 30/09/2026 | G13: Tipo Frete: | H13: CIF | I13: Cond. Pag.: | J13: 30/60/90 Dias
A14: % OFF: | B14: 0% | C14: % Nota: | D14: 100% | E14: Observações: | F14: Agendar descarregamento com antecedência. Entrega no CD Irati - Paletizado padrão PBR.
A16: # | B16: CÓDIGO FORNECEDOR | C16: CÓDIGO INTERNO (PRD) | D16: CÓDIGO BARRAS (EAN-13) | E16: DESCRIÇÃO DO PRODUTO | F16: NCM | G16: UNID. | H16: QTD/CX | I16: QTD CX | J16: TOTAL PEÇAS | K16: PREÇO UNIT. (R$)
A17: 1 | B17: 652 | C17: PRD-001 | D17: 7891234560012 | E17: INCENSARIO MOTIVACIONAL EM MADEIRA 25CM | F17: 4421.99.00 | G17: CX | H17: 6 | I17: 20 | J17: =H17*I17 -> 120 | K17: 4.7
A18: 2 | B18: 653 | C18: PRD-002 | D18: 7891234560029 | E18: KIT PETISQUEIRA QUADRADA BAMBU COM 3 DIVISORIAS | F18: 4419.19.00 | G18: CX | H18: 6 | I18: 15 | J18: =H18*I18 -> 90 | K18: 6.5
A19: 3 | B19: 654 | C19: PRD-003 | D19: 7891234560036 | E19: KIT PETISQUEIRA RETANGULAR 4 DIVISORIAS | F19: 4419.19.00 | G19: CX | H19: 6 | I19: 12 | J19: =H19*I19 -> 72 | K19: 6.5
A20: 4 | B20: 656 | C20: PRD-004 | D20: 7891234560043 | E20: PORTA TEMPERO TABUA GIRATORIA C/ 5 POTES VIDRO | F20: 7013.49.00 | G20: CX | H20: 6 | I20: 18 | J20: =H20*I20 -> 108 | K20: 7.4
A21: 5 | B21: 657 | D21: 7891234560050 | E21: QUADRO MINHAS COMPRAS MAGNETICO 11X30CM C/ CANETA | F21: 4911.99.00 | G21: CX | H21: 12 | I21: 10 | J21: =H21*I21 -> 120 | K21: 6.2
A22: 6 | G22: UN | H22: 1 | J22: =IF(I22>0,H22*I22,0) -> 0
A23: 7 | G23: UN | H23: 1 | J23: =IF(I23>0,H23*I23,0) -> 0
A24: 8 | G24: UN | H24: 1 | J24: =IF(I24>0,H24*I24,0) -> 0
A25: 9 | G25: UN | H25: 1 | J25: =IF(I25>0,H25*I25,0) -> 0
A26: 10 | G26: UN | H26: 1 | J26: =IF(I26>0,H26*I26,0) -> 0
A27: 11 | G27: UN | H27: 1 | J27: =IF(I27>0,H27*I27,0) -> 0
A28: 12 | G28: UN | H28: 1 | J28: =IF(I28>0,H28*I28,0) -> 0
A29: 13 | G29: UN | H29: 1 | J29: =IF(I29>0,H29*I29,0) -> 0
A30: 14 | G30: UN | H30: 1 | J30: =IF(I30>0,H30*I30,0) -> 0
A31: 15 | G31: UN | H31: 1 | J31: =IF(I31>0,H31*I31,0) -> 0
A32: 16 | G32: UN | H32: 1 | J32: =IF(I32>0,H32*I32,0) -> 0
A33: 17 | G33: UN | H33: 1 | J33: =IF(I33>0,H33*I33,0) -> 0
... A36: 20 | G36: UN | H36: 1 | J36: =IF(I36>0,H36*I36,0) -> 0
A37: TOTAIS CONSOLIDADOS DO PEDIDO: | I37: =SUM(I17:I36) -> 75 | J37: =SUM(J17:J36) -> 516
A39: REGRAS MANDATÓRIAS DE RECEBIMENTO & FATURAMENTO (REDE MEGA 12 - CD IRATI):
A40: 1. Boletos NÃO devem exceder o valor de R$ 9.999,00 por título.
A41: 2. Boletos e arquivo XML da Nota Fiscal devem ser enviados obrigatoriamente para: als.conecta@gmail.com.
A42: 3. Descarregamento no local de entrega sob responsabilidade integral do fornecedor / transportadora.
A43: 4. Agendar previamente a data de descarregamento no WhatsApp da Logística: (42) 9 9136-5009 (Roberta).
A44: 5. As quantidades recebidas serão conferidas por bipagem e inspeção de avarias; divergências serão debitadas do pagamento.

Sheet SEPARACAO POR LOJA
A1: REDE MEGA 12 • GRADE DE SEPARAÇÃO E DISTRIBUIÇÃO DAS 20 LOJAS
A2: Distribuição por filial em Unidades (UN). As quantidades alocadas devem bater exatamente com o total comprado do item.
A3: DADOS DO ITEM COMPRADO | F3: CD | G3: CLUSTER A (8 LOJAS PRINCIPAIS - MAIOR VOLUME) | O3: CLUSTER B (8 LOJAS MÉDIAS) | W3: CLUSTER C (4 LOJAS COMPACTAS) | AA3: AUDITORIA DA GRADE
A4: # | B4: CÓDIGO FORNEC. | C4: CÓDIGO INTERNO | D4: DESCRIÇÃO DO PRODUTO | E4: TOTAL PEDIDO | F4: RESERVA CD | G4: PONTA GROSSA CENTRO | H4: RESERVA | I4: TIBAGI | J4: NOVA RÚSSIA | K4: JAVERT | L4: IVAÍ | M4: IRATI CENTRO | N4: CAMPO LARGO | O4: CASTRO | P4: IMBITUVA | Q4: SANTA PAULA | R4: PRUDENTÓPOLIS | S4: GUARAPUAVA | T4: IMBAÚ | U4: RIO AZUL | V4: REBOUÇAS | W4: DEPÓSITO CENTRAL | X4: TEIXEIRA SOARES | Y4: MALLET | Z4: IPIRANGA | AA4: TOTAL ALOCADO | AB4: CONFERÊNCIA
A5: 1 | B5: =='PEDIDO COMERCIAL'!B17 -> 652 | C5: =='PEDIDO COMERCIAL'!C17 -> PRD-001 | D5: =='PEDIDO COMERCIAL'!E17 -> INCENSARIO MOTIVACIONAL EM MADEIRA 25CM | E5: =='PEDIDO COMERCIAL'!J17 -> 120 | F5: 12 | G5: 7 | H5: 7 | I5: 7 | J5: 7 | K5: 7 | L5: 7 | M5: 7 | N5: 7 | O5: 5 | P5: 5 | Q5: 5 | R5: 5 | S5: 5 | T5: 5 | U5: 5 | V5: 5 | W5: 3 | X5: 3 | Y5: 3 | Z5: 3 | AA5: =SUM(F5:Z5) -> 120 | AB5: =IF(AA5=E5,"OK (100%)","DIVERGENTE") -> OK (100%)
A6: 2 | B6: =='PEDIDO COMERCIAL'!B18 -> 653 | C6: =='PEDIDO COMERCIAL'!C18 -> PRD-002 | D6: =='PEDIDO COMERCIAL'!E18 -> KIT PETISQUEIRA QUADRADA BAMBU COM 3 DIVISORIAS | E6: =='PEDIDO COMERCIAL'!J18 -> 90 | F6: 9 | G6: 5 | H6: 5 | I6: 5 | J6: 5 | K6: 5 | L6: 5 | M6: 5 | N6: 5 | O6: 4 | P6: 4 | Q6: 4 | R6: 4 | S6: 4 | T6: 4 | U6: 4 | V6: 4 | W6: 2 | X6: 2 | Y6: 2 | Z6: 2 | AA6: =SUM(F6:Z6) -> 90 | AB6: =IF(AA6=E6,"OK (100%)","DIVERGENTE") -> OK (100%)
A7: 3 | B7: =='PEDIDO COMERCIAL'!B19 -> 654 | C7: =='PEDIDO COMERCIAL'!C19 -> PRD-003 | D7: =='PEDIDO COMERCIAL'!E19 -> KIT PETISQUEIRA RETANGULAR 4 DIVISORIAS | E7: =='PEDIDO COMERCIAL'!J19 -> 72 | F7: 7 | G7: 4 | H7: 4 | I7: 4 | J7: 4 | K7: 4 | L7: 4 | M7: 4 | N7: 4 | O7: 3 | P7: 3 | Q7: 3 | R7: 3 | S7: 3 | T7: 3 | U7: 3 | V7: 3 | W7: 2 | X7: 2 | Y7: 2 | Z7: 2 | AA7: =SUM(F7:Z7) -> 72 | AB7: =IF(AA7=E7,"OK (100%)","DIVERGENTE") -> OK (100%)
A8: 4 | B8: =='PEDIDO COMERCIAL'!B20 -> 656 | C8: =='PEDIDO COMERCIAL'!C20 -> PRD-004 | D8: =='PEDIDO COMERCIAL'!E20 -> PORTA TEMPERO TABUA GIRATORIA C/ 5 POTES VIDRO | E8: =='PEDIDO COMERCIAL'!J20 -> 108 | F8: 11 | G8: 6 | H8: 6 | I8: 6 | J8: 6 | K8: 6 | L8: 6 | M8: 6 | N8: 6 | O8: 4 | P8: 4 | Q8: 4 | R8: 4 | S8: 4 | T8: 4 | U8: 4 | V8: 4 | W8: 4 | X8: 4 | Y8: 4 | Z8: 4 | AA8: =SUM(F8:Z8) -> 108 | AB8: =IF(AA8=E8,"OK (100%)","DIVERGENTE") -> OK (100%)
A9: 5 | B9: =='PEDIDO COMERCIAL'!B21 -> 657 | C9: =='PEDIDO COMERCIAL'!C21 | D9: =='PEDIDO COMERCIAL'!E21 -> QUADRO MINHAS COMPRAS MAGNETICO 11X30CM C/ CANETA | E9: =='PEDIDO COMERCIAL'!J21 -> 120 | F9: 12 | G9: 7 | H9: 7 | I9: 7 | J9: 7 | K9: 7 | L9: 7 | M9: 7 | N9: 7 | O9: 5 | P9: 5 | Q9: 5 | R9: 5 | S9: 5 | T9: 5 | U9: 5 | V9: 5 | W9: 3 | X9: 3 | Y9: 3 | Z9: 3 | AA9: =SUM(F9:Z9) -> 120 | AB9: =IF(AA9=E9,"OK (100%)","DIVERGENTE") -> OK (100%)

Sheet INSTRUCOES DE PREENCHIMENTO
B2: GUIA OFICIAL DE PREENCHIMENTO DA PLANILHA (REDE MEGA 12)
B3: Siga as orientações abaixo para garantir 100% de sucesso na importação e geração da proposta comercial.
B5: CAMPO / COLUNA | C5: OBRIGATÓRIO? | D5: TIPO / FORMATO | E5: COMO PREENCHER & ORIENTAÇÕES
B6: Fornecedor / Razão Social | C6: SIM | D6: Texto | E6: Nome oficial ou razão social da empresa fornecedora. O sistema vincula automaticamente com o cadastro interno.
B7: CNPJ do Fornecedor | C7: RECOMENDADO | D7: 00.000.000/0001-00 | E7: Identificador fiscal único para garantir o vínculo sem duplicidades.
B8: Vendedor & Contatos | C8: RECOMENDADO | D8: Texto / Telefone | E8: Nome do representante e telefone/WhatsApp para constar no espelho oficial do pedido.
B9: Tipo de Frete | C9: SIM | D9: CIF / FOB / Retira | E9: CIF: Por conta do fornecedor. FOB: Frete a cobrar/pago pela Mega 12. Retira: Retirada no local.
B10: Condição de Pagamento | C10: SIM | D10: Texto / Prazos | E10: Exemplos: 30/60/90 Dias, Boleto 30 Dias, À Vista. O sistema gera automaticamente o fluxo de duplicatas financeiras.
B11: % OFF / Desconto Comercial | C11: OPCIONAL | D11: Percentual (%) | E11: Percentual de desconto comercial negociado sobre o pedido (ex: 0%, 5%, 10%). O sistema registra no cabeçalho e preserva os preços unitários líquidos da grade.
B12: % NOTA FISCAL | C12: OPCIONAL | D12: Percentual (%) | E12: Percentual do valor faturado oficialmente em Nota Fiscal (padrão: 100%). Usado para controle fiscal e histórico.
B13: CÓDIGO FORNECEDOR | C13: SIM | D13: Texto ou Número | E13: Referência do item de acordo com a tabela do fornecedor (ex: 652, REF-1020).
B14: CÓDIGO INTERNO (PRD) | C14: OPCIONAL | D14: PRD-XXXX | E14: Se o item já estiver cadastrado no catálogo Mega 12, informe aqui. Se estiver em branco, o sistema cria um novo código automaticamente.
B15: CÓDIGO BARRAS (EAN-13) | C15: OPCIONAL | D15: 13 dígitos | E15: Código GTIN/EAN-13 da embalagem ou unidade. Essencial para conferência rápida por coletor de doca.
B16: DESCRIÇÃO DO PRODUTO | C16: SIM | D16: Texto Completo | E16: Nome claro do produto, material, dimensões ou modelo.
... B23: Aba SEPARAÇÃO POR LOJA | C23: OPCIONAL | D23: Grade por Filial | E23: Se preenchida, o sistema importa as quantidades exatas por filial. Se deixada em branco, o sistema calcula a divisão automática ideal pelos clusters A/B/C.

Sheet PARAMETROS FISCAIS
B2: PARÂMETROS FISCAIS DE REFERÊNCIA (REDE MEGA 12 - PARANÁ)
B4: PARÂMETRO TRIBUTÁRIO | C4: ALÍQUOTA | D4: DESCRIÇÃO E APLICAÇÃO
B5: ICMS Entrada (Crédito) | C5: 12.0% | D5: Crédito tributário abatido do custo do produto na entrada estadual
B6: Custos Fixos Operacionais | C6: 26.0% | D6: Percentual operacional incidente sobre o PDV nas lojas físicas
B7: ICMS Saída (Alíquota PR) | C7: 19.5% | D7: Alíquota de ICMS sobre a venda final no Estado do Paraná
B8: PIS / COFINS / IR | C8: 6.0% | D8: Impostos federais incidentes sobre o faturamento de saída
B9: IPI Padrão | C9: 0.0% | D9: Imposto sobre Produtos Industrializados (quando aplicável por NCM)
B10: ST (Substituição Tributária) | C10: 0.0% | D10: ICMS-ST destacado por fornecedor (quando aplicável)
