Workbook

Sheet PEDIDO COMERCIAL
A1: REDE MEGA 12 • PLANILHA MODELO DE IMPORTAÇÃO DE PEDIDOS | G1: MODELO OFICIAL V2.0
A2: ALS 10 BAZAR E BRINQUEDOS LTDA • ESTRUTURA INTELIGENTE ANTI-ERRO | G2: Uso: Compras e Fornecedores
A3: ℹ️ INSTRUÇÕES: Preencha os Dados do Fornecedor, Condições e Produtos. A coluna TOTAL PEÇAS calcula automaticamente (= QTD/CX × QTD CX).
A5: 1. DADOS DA EMPRESA COMPRADORA (DESTINATÁRIO - MEGA 12): | E5: 2. DADOS DO FORNECEDOR & VENDEDOR (PREENCHA SEUS DADOS):
A6: Razão Social: | B6: ALS 10 BAZAR E BRINQUEDOS LTDA | E6: Razão Social:
A7: CNPJ / IE: | B7: 37.144.240/0001-70 IE: 90847822-35 | E7: CNPJ:
A8: End. Entrega: | B8: Av. José Galiciolli, 152 – BR153 – Centro – Irati – PR (CEP: 84500-009) | E8: Vendedor:
A9: Boletos / XML: | B9: als.conecta@gmail.com | E9: WhatsApp / Fone:
A10: Compras: | B10: Rafael (55) 9 9659-6315 | Bruna (55) 9 3618-5609 | E10: E-mail Vendas:
A12: 3. CONDIÇÕES COMERCIAIS, PRAZOS & FRETE:
A13: Nº Pedido: | C13: Data Pedido: | D13: 14/09/2026 | E13: Entrega: | F13: 30/09/2026 | G13: Tipo Frete: | H13: CIF
A14: Cond. Pag.: | B14: 30/60/90 Dias | C14: % OFF: | D14: 0% | E14: Observações: | F14: Agendar descarregamento no CD Irati - Paletizado padrão PBR.
A16: # | B16: CÓDIGO FORNECEDOR | C16: DESCRIÇÃO DO PRODUTO | D16: UNID. | E16: QTD/CX | F16: QTD CX | G16: TOTAL PEÇAS | H16: PREÇO UNIT. (R$)
A17: 1 | B17: 284 | C17: CAIXA ORGANIZADORA 9L TRANSPARENTE | E17: 12 | G17: =IF(F17>0,IF(E17>0,E17*F17,F17),"") -> #VALUE!
A18: 2 | B18: 318 | C18: CAIXA ORGANIZADORA 9L COLOR PRIME | E18: 12 | G18: =IF(F18>0,IF(E18>0,E18*F18,F18),"") -> #VALUE!
A19: 3 | B19: 402 | C19: CAIXA ORGANIZADORA 9L PRETA | E19: 12 | G19: =IF(F19>0,IF(E19>0,E19*F19,F19),"") -> #VALUE!
A20: 4 | B20: 411 | C20: CAIXA ORGANIZADORA 15L PRETA | E20: 12 | G20: =IF(F20>0,IF(E20>0,E20*F20,F20),"") -> #VALUE!
A21: 5 | B21: 283 | C21: CAIXA ORGANIZADORA 15L TRANSPARENTE | E21: 12 | G21: =IF(F21>0,IF(E21>0,E21*F21,F21),"") -> #VALUE!
A22: 6 | B22: 410 | C22: CAIXA ORGANIZADORA 15L COLOR PRIME | E22: 12 | G22: =IF(F22>0,IF(E22>0,E22*F22,F22),"") -> #VALUE!
A23: 7 | B23: 303 | C23: ESCORREDOR DE LOUÇA PRETO | E23: 6 | G23: =IF(F23>0,IF(E23>0,E23*F23,F23),"") -> #VALUE!
A24: 8 | B24: 181 | C24: ESCORREDOR DE LOUÇA PRIME COLOR | E24: 6 | G24: =IF(F24>0,IF(E24>0,E24*F24,F24),"") -> #VALUE!
A25: 9 | B25: 347 | C25: KIT VASO GREGO RED. PTO 3PÇS PMG | E25: 6 | G25: =IF(F25>0,IF(E25>0,E25*F25,F25),"") -> #VALUE!
A26: 10 | B26: 91 | C26: KIT VASO QUAD. PTO 3PÇS PMG | E26: 6 | G26: =IF(F26>0,IF(E26>0,E26*F26,F26),"") -> #VALUE!
A27: 11 | B27: 342 | C27: VASO GREGO PTO REDONDO 9L | E27: 12 | G27: =IF(F27>0,IF(E27>0,E27*F27,F27),"") -> #VALUE!
A28: 12 | B28: 341 | C28: VASO GREGO COLOR REDONDO 9L | E28: 12 | G28: =IF(F28>0,IF(E28>0,E28*F28,F28),"") -> #VALUE!
A29: 13 | B29: 49 | C29: VASO PRETO QUAD. 16L | E29: 12 | G29: =IF(F29>0,IF(E29>0,E29*F29,F29),"") -> #VALUE!
... A63: 26 | B63: 453 | C63: CESTO TELADO RET. RATAN 45L | E63: 6 | G63: =IF(F63>0,IF(E63>0,E63*F63,F63),"") -> #VALUE!
A64: 27 | G64: =IF(F64>0,IF(E64>0,E64*F64,F64),"") -> #VALUE!
A65: 28 | G65: =IF(F65>0,IF(E65>0,E65*F65,F65),"") -> #VALUE!
A66: 29 | G66: =IF(F66>0,IF(E66>0,E66*F66,F66),"") -> #VALUE!
A67: 30 | G67: =IF(F67>0,IF(E67>0,E67*F67,F67),"") -> #VALUE!
A68: TOTAIS CONSOLIDADOS DO PEDIDO: | F68: =SUM(F17:F67) -> 0 | G68: =SUM(G17:G67) -> #VALUE!
A70: REGRAS MANDATÓRIAS DE RECEBIMENTO & FATURAMENTO (REDE MEGA 12 - CD IRATI):
A71: 1. Boletos NÃO devem exceder o valor de R$ 9.999,00 por título.
A72: 2. Boletos e arquivo XML da Nota Fiscal devem ser enviados obrigatoriamente para: als.conecta@gmail.com.
A73: 3. Descarregamento no local de entrega sob responsabilidade integral do fornecedor / transportadora.
A74: 4. Agendar previamente a data de descarregamento no WhatsApp da Logística: (42) 9 9136-5009 (Roberta).
A75: 5. As quantidades recebidas serão conferidas por bipagem e inspeção de avarias; divergências serão debitadas do pagamento.

Sheet SEPARACAO POR LOJA
A1: REDE MEGA 12 • GRADE DE SEPARAÇÃO E DISTRIBUIÇÃO DAS 20 LOJAS
A2: Distribuição por filial em Unidades (UN). As quantidades alocadas devem bater exatamente com o total comprado do item.
A3: DADOS DO ITEM COMPRADO | E3: CD | F3: CLUSTER A (8 LOJAS PRINCIPAIS - MAIOR VOLUME) | N3: CLUSTER B (8 LOJAS MÉDIAS) | V3: CLUSTER C (4 LOJAS COMPACTAS) | Z3: AUDITORIA DA GRADE
A4: # | B4: CÓDIGO FORNEC. | C4: DESCRIÇÃO DO PRODUTO | D4: TOTAL PEDIDO | E4: RESERVA CD | F4: PONTA GROSSA CENTRO | G4: RESERVA | H4: TIBAGI | I4: NOVA RÚSSIA | J4: JAVERT | K4: IVAÍ | L4: IRATI CENTRO | M4: CAMPO LARGO | N4: CASTRO | O4: IMBITUVA | P4: SANTA PAULA | Q4: PRUDENTÓPOLIS | R4: GUARAPUAVA | S4: IMBAÚ | T4: RIO AZUL | U4: REBOUÇAS | V4: DEPÓSITO CENTRAL | W4: TEIXEIRA SOARES | X4: MALLET | Y4: IPIRANGA | Z4: TOTAL ALOCADO | AA4: CONFERÊNCIA
A5: 1 | B5: =IF('PEDIDO COMERCIAL'!B17="","",'PEDIDO COMERCIAL'!B17) -> 284 | C5: =IF('PEDIDO COMERCIAL'!C17="","",'PEDIDO COMERCIAL'!C17) -> CAIXA ORGANIZADORA 9L TRANSPARENTE | D5: =IF('PEDIDO COMERCIAL'!G17="","",'PEDIDO COMERCIAL'!G17) -> #VALUE! | Z5: =IF(OR(D5="",COUNT(E5:Y5)=0),"",SUM(E5:Y5)) -> #VALUE! | AA5: =IF(OR(D5="",D5=0),"",IF(Z5=D5,"OK (100%)","DIVERGENTE")) -> #VALUE!
A6: 2 | B6: =IF('PEDIDO COMERCIAL'!B18="","",'PEDIDO COMERCIAL'!B18) -> 318 | C6: =IF('PEDIDO COMERCIAL'!C18="","",'PEDIDO COMERCIAL'!C18) -> CAIXA ORGANIZADORA 9L COLOR PRIME | D6: =IF('PEDIDO COMERCIAL'!G18="","",'PEDIDO COMERCIAL'!G18) -> #VALUE! | Z6: =IF(OR(D6="",COUNT(E6:Y6)=0),"",SUM(E6:Y6)) -> #VALUE! | AA6: =IF(OR(D6="",D6=0),"",IF(Z6=D6,"OK (100%)","DIVERGENTE")) -> #VALUE!
A7: 3 | B7: =IF('PEDIDO COMERCIAL'!B19="","",'PEDIDO COMERCIAL'!B19) -> 402 | C7: =IF('PEDIDO COMERCIAL'!C19="","",'PEDIDO COMERCIAL'!C19) -> CAIXA ORGANIZADORA 9L PRETA | D7: =IF('PEDIDO COMERCIAL'!G19="","",'PEDIDO COMERCIAL'!G19) -> #VALUE! | Z7: =IF(OR(D7="",COUNT(E7:Y7)=0),"",SUM(E7:Y7)) -> #VALUE! | AA7: =IF(OR(D7="",D7=0),"",IF(Z7=D7,"OK (100%)","DIVERGENTE")) -> #VALUE!
A8: 4 | B8: =IF('PEDIDO COMERCIAL'!B20="","",'PEDIDO COMERCIAL'!B20) -> 411 | C8: =IF('PEDIDO COMERCIAL'!C20="","",'PEDIDO COMERCIAL'!C20) -> CAIXA ORGANIZADORA 15L PRETA | D8: =IF('PEDIDO COMERCIAL'!G20="","",'PEDIDO COMERCIAL'!G20) -> #VALUE! | Z8: =IF(OR(D8="",COUNT(E8:Y8)=0),"",SUM(E8:Y8)) -> #VALUE! | AA8: =IF(OR(D8="",D8=0),"",IF(Z8=D8,"OK (100%)","DIVERGENTE")) -> #VALUE!
A9: 5 | B9: =IF('PEDIDO COMERCIAL'!B21="","",'PEDIDO COMERCIAL'!B21) -> 283 | C9: =IF('PEDIDO COMERCIAL'!C21="","",'PEDIDO COMERCIAL'!C21) -> CAIXA ORGANIZADORA 15L TRANSPARENTE | D9: =IF('PEDIDO COMERCIAL'!G21="","",'PEDIDO COMERCIAL'!G21) -> #VALUE! | Z9: =IF(OR(D9="",COUNT(E9:Y9)=0),"",SUM(E9:Y9)) -> #VALUE! | AA9: =IF(OR(D9="",D9=0),"",IF(Z9=D9,"OK (100%)","DIVERGENTE")) -> #VALUE!
A10: 6 | B10: =IF('PEDIDO COMERCIAL'!B22="","",'PEDIDO COMERCIAL'!B22) -> 410 | C10: =IF('PEDIDO COMERCIAL'!C22="","",'PEDIDO COMERCIAL'!C22) -> CAIXA ORGANIZADORA 15L COLOR PRIME | D10: =IF('PEDIDO COMERCIAL'!G22="","",'PEDIDO COMERCIAL'!G22) -> #VALUE! | Z10: =IF(OR(D10="",COUNT(E10:Y10)=0),"",SUM(E10:Y10)) -> #VALUE! | AA10: =IF(OR(D10="",D10=0),"",IF(Z10=D10,"OK (100%)","DIVERGENTE")) -> #VALUE!
A11: 7 | B11: =IF('PEDIDO COMERCIAL'!B23="","",'PEDIDO COMERCIAL'!B23) -> 303 | C11: =IF('PEDIDO COMERCIAL'!C23="","",'PEDIDO COMERCIAL'!C23) -> ESCORREDOR DE LOUÇA PRETO | D11: =IF('PEDIDO COMERCIAL'!G23="","",'PEDIDO COMERCIAL'!G23) -> #VALUE! | Z11: =IF(OR(D11="",COUNT(E11:Y11)=0),"",SUM(E11:Y11)) -> #VALUE! | AA11: =IF(OR(D11="",D11=0),"",IF(Z11=D11,"OK (100%)","DIVERGENTE")) -> #VALUE!
A12: 8 | B12: =IF('PEDIDO COMERCIAL'!B24="","",'PEDIDO COMERCIAL'!B24) -> 181 | C12: =IF('PEDIDO COMERCIAL'!C24="","",'PEDIDO COMERCIAL'!C24) -> ESCORREDOR DE LOUÇA PRIME COLOR | D12: =IF('PEDIDO COMERCIAL'!G24="","",'PEDIDO COMERCIAL'!G24) -> #VALUE! | Z12: =IF(OR(D12="",COUNT(E12:Y12)=0),"",SUM(E12:Y12)) -> #VALUE! | AA12: =IF(OR(D12="",D12=0),"",IF(Z12=D12,"OK (100%)","DIVERGENTE")) -> #VALUE!
A13: 9 | B13: =IF('PEDIDO COMERCIAL'!B25="","",'PEDIDO COMERCIAL'!B25) -> 347 | C13: =IF('PEDIDO COMERCIAL'!C25="","",'PEDIDO COMERCIAL'!C25) -> KIT VASO GREGO RED. PTO 3PÇS PMG | D13: =IF('PEDIDO COMERCIAL'!G25="","",'PEDIDO COMERCIAL'!G25) -> #VALUE! | Z13: =IF(OR(D13="",COUNT(E13:Y13)=0),"",SUM(E13:Y13)) -> #VALUE! | AA13: =IF(OR(D13="",D13=0),"",IF(Z13=D13,"OK (100%)","DIVERGENTE")) -> #VALUE!
A14: 10 | B14: =IF('PEDIDO COMERCIAL'!B47="","",'PEDIDO COMERCIAL'!B47) -> 383 | C14: =IF('PEDIDO COMERCIAL'!C47="","",'PEDIDO COMERCIAL'!C47) -> VASO ROMA QUADRADO COLOR G 21L | D14: =IF('PEDIDO COMERCIAL'!G47="","",'PEDIDO COMERCIAL'!G47) -> #VALUE! | Z14: =IF(OR(D14="",COUNT(E14:Y14)=0),"",SUM(E14:Y14)) -> #VALUE! | AA14: =IF(OR(D14="",D14=0),"",IF(Z14=D14,"OK (100%)","DIVERGENTE")) -> #VALUE!
A15: 11 | B15: =IF('PEDIDO COMERCIAL'!B48="","",'PEDIDO COMERCIAL'!B48) -> 336 | C15: =IF('PEDIDO COMERCIAL'!C48="","",'PEDIDO COMERCIAL'!C48) -> VASO ROMA QUADRADO PRETO G 16,5L | D15: =IF('PEDIDO COMERCIAL'!G48="","",'PEDIDO COMERCIAL'!G48) -> #VALUE! | Z15: =IF(OR(D15="",COUNT(E15:Y15)=0),"",SUM(E15:Y15)) -> #VALUE! | AA15: =IF(OR(D15="",D15=0),"",IF(Z15=D15,"OK (100%)","DIVERGENTE")) -> #VALUE!
A16: 12 | B16: =IF('PEDIDO COMERCIAL'!B49="","",'PEDIDO COMERCIAL'!B49) -> 366 | C16: =IF('PEDIDO COMERCIAL'!C49="","",'PEDIDO COMERCIAL'!C49) -> VASO ROMA QUADRADO PRETO G 10L | D16: =IF('PEDIDO COMERCIAL'!G49="","",'PEDIDO COMERCIAL'!G49) -> #VALUE! | Z16: =IF(OR(D16="",COUNT(E16:Y16)=0),"",SUM(E16:Y16)) -> #VALUE! | AA16: =IF(OR(D16="",D16=0),"",IF(Z16=D16,"OK (100%)","DIVERGENTE")) -> #VALUE!
A17: 13 | B17: =IF('PEDIDO COMERCIAL'!B50="","",'PEDIDO COMERCIAL'!B50) -> 335 | C17: =IF('PEDIDO COMERCIAL'!C50="","",'PEDIDO COMERCIAL'!C50) -> VASO ROMA QUADRADO COLOR G 16,5L | D17: =IF('PEDIDO COMERCIAL'!G50="","",'PEDIDO COMERCIAL'!G50) -> #VALUE! | Z17: =IF(OR(D17="",COUNT(E17:Y17)=0),"",SUM(E17:Y17)) -> #VALUE! | AA17: =IF(OR(D17="",D17=0),"",IF(Z17=D17,"OK (100%)","DIVERGENTE")) -> #VALUE!
A18: 14 | B18: =IF('PEDIDO COMERCIAL'!B51="","",'PEDIDO COMERCIAL'!B51) -> 365 | C18: =IF('PEDIDO COMERCIAL'!C51="","",'PEDIDO COMERCIAL'!C51) -> VASO ROMA QUADRADO COLOR G 10L | D18: =IF('PEDIDO COMERCIAL'!G51="","",'PEDIDO COMERCIAL'!G51) -> #VALUE! | Z18: =IF(OR(D18="",COUNT(E18:Y18)=0),"",SUM(E18:Y18)) -> #VALUE! | AA18: =IF(OR(D18="",D18=0),"",IF(Z18=D18,"OK (100%)","DIVERGENTE")) -> #VALUE!
A19: 15 | B19: =IF('PEDIDO COMERCIAL'!B52="","",'PEDIDO COMERCIAL'!B52) -> 378 | C19: =IF('PEDIDO COMERCIAL'!C52="","",'PEDIDO COMERCIAL'!C52) -> BALDE REFORÇADO DE PEDREIRO 12L | D19: =IF('PEDIDO COMERCIAL'!G52="","",'PEDIDO COMERCIAL'!G52) -> #VALUE! | Z19: =IF(OR(D19="",COUNT(E19:Y19)=0),"",SUM(E19:Y19)) -> #VALUE! | AA19: =IF(OR(D19="",D19=0),"",IF(Z19=D19,"OK (100%)","DIVERGENTE")) -> #VALUE!
A20: 16 | B20: =IF('PEDIDO COMERCIAL'!B53="","",'PEDIDO COMERCIAL'!B53) -> 230 | C20: =IF('PEDIDO COMERCIAL'!C53="","",'PEDIDO COMERCIAL'!C53) -> CESTOMULTIUSO C/ TRAVA 60L | D20: =IF('PEDIDO COMERCIAL'!G53="","",'PEDIDO COMERCIAL'!G53) -> #VALUE! | Z20: =IF(OR(D20="",COUNT(E20:Y20)=0),"",SUM(E20:Y20)) -> #VALUE! | AA20: =IF(OR(D20="",D20=0),"",IF(Z20=D20,"OK (100%)","DIVERGENTE")) -> #VALUE!
A21: 17 | B21: =IF('PEDIDO COMERCIAL'!B54="","",'PEDIDO COMERCIAL'!B54) -> 486 | C21: =IF('PEDIDO COMERCIAL'!C54="","",'PEDIDO COMERCIAL'!C54) -> KIT 10 POTES 300ML | D21: =IF('PEDIDO COMERCIAL'!G54="","",'PEDIDO COMERCIAL'!G54) -> #VALUE! | Z21: =IF(OR(D21="",COUNT(E21:Y21)=0),"",SUM(E21:Y21)) -> #VALUE! | AA21: =IF(OR(D21="",D21=0),"",IF(Z21=D21,"OK (100%)","DIVERGENTE")) -> #VALUE!
A22: 18 | B22: =IF('PEDIDO COMERCIAL'!B55="","",'PEDIDO COMERCIAL'!B55) -> 485 | C22: =IF('PEDIDO COMERCIAL'!C55="","",'PEDIDO COMERCIAL'!C55) -> KIT 6 POTES 700ML | D22: =IF('PEDIDO COMERCIAL'!G55="","",'PEDIDO COMERCIAL'!G55) -> #VALUE! | Z22: =IF(OR(D22="",COUNT(E22:Y22)=0),"",SUM(E22:Y22)) -> #VALUE! | AA22: =IF(OR(D22="",D22=0),"",IF(Z22=D22,"OK (100%)","DIVERGENTE")) -> #VALUE!
A23: 19 | B23: =IF('PEDIDO COMERCIAL'!B56="","",'PEDIDO COMERCIAL'!B56) -> 196 | C23: =IF('PEDIDO COMERCIAL'!C56="","",'PEDIDO COMERCIAL'!C56) -> KIT 4 POTES 1400ML | D23: =IF('PEDIDO COMERCIAL'!G56="","",'PEDIDO COMERCIAL'!G56) -> #VALUE! | Z23: =IF(OR(D23="",COUNT(E23:Y23)=0),"",SUM(E23:Y23)) -> #VALUE! | AA23: =IF(OR(D23="",D23=0),"",IF(Z23=D23,"OK (100%)","DIVERGENTE")) -> #VALUE!
A24: 20 | B24: =IF('PEDIDO COMERCIAL'!B57="","",'PEDIDO COMERCIAL'!B57) -> 186 | C24: =IF('PEDIDO COMERCIAL'!C57="","",'PEDIDO COMERCIAL'!C57) -> KIT 2 SALADEIRAS 5L | D24: =IF('PEDIDO COMERCIAL'!G57="","",'PEDIDO COMERCIAL'!G57) -> #VALUE! | Z24: =IF(OR(D24="",COUNT(E24:Y24)=0),"",SUM(E24:Y24)) -> #VALUE! | AA24: =IF(OR(D24="",D24=0),"",IF(Z24=D24,"OK (100%)","DIVERGENTE")) -> #VALUE!
A25: 21 | B25: =IF('PEDIDO COMERCIAL'!B58="","",'PEDIDO COMERCIAL'!B58) -> 528 | C25: =IF('PEDIDO COMERCIAL'!C58="","",'PEDIDO COMERCIAL'!C58) -> KIT 3 POTES RETANGULAR PRIME 3,3L | D25: =IF('PEDIDO COMERCIAL'!G58="","",'PEDIDO COMERCIAL'!G58) -> #VALUE! | Z25: =IF(OR(D25="",COUNT(E25:Y25)=0),"",SUM(E25:Y25)) -> #VALUE! | AA25: =IF(OR(D25="",D25=0),"",IF(Z25=D25,"OK (100%)","DIVERGENTE")) -> #VALUE!
... A34: 30 | B34: =IF('PEDIDO COMERCIAL'!B67="","",'PEDIDO COMERCIAL'!B67) | C34: =IF('PEDIDO COMERCIAL'!C67="","",'PEDIDO COMERCIAL'!C67) | D34: =IF('PEDIDO COMERCIAL'!G67="","",'PEDIDO COMERCIAL'!G67) -> #VALUE! | Z34: =IF(OR(D34="",COUNT(E34:Y34)=0),"",SUM(E34:Y34)) -> #VALUE! | AA34: =IF(OR(D34="",D34=0),"",IF(Z34=D34,"OK (100%)","DIVERGENTE")) -> #VALUE!
A35: TOTAL GERAL DA SEPARAÇÃO POR FILIAL: | D35: =SUM(D5:D34) -> #VALUE! | E35: =SUM(E5:E34) -> 0 | F35: =SUM(F5:F34) -> 0 | G35: =SUM(G5:G34) -> 0 | H35: =SUM(H5:H34) -> 0 | I35: =SUM(I5:I34) -> 0 | J35: =SUM(J5:J34) -> 0 | K35: =SUM(K5:K34) -> 0 | ... Z35: =SUM(Z5:Z34) -> #VALUE! | AA35: =IF(D35=0,"",IF(Z35=D35,"OK (100%)","DIVERGENTE")) -> #VALUE!

Sheet INSTRUCOES DE PREENCHIMENTO
B2: GUIA OFICIAL DE PREENCHIMENTO DA PLANILHA (REDE MEGA 12)
B3: Siga as orientações abaixo para garantir 100% de sucesso na importação e geração da proposta comercial.
B5: CAMPO / COLUNA | C5: OBRIGATÓRIO? | D5: TIPO / FORMATO | E5: COMO PREENCHER & ORIENTAÇÕES
B6: Fornecedor / Razão Social | C6: SIM | D6: Texto | E6: Nome oficial ou razão social da empresa fornecedora. O sistema vincula automaticamente com o cadastro interno.
B7: CNPJ do Fornecedor | C7: RECOMENDADO | D7: 00.000.000/0001-00 | E7: Identificador fiscal único para garantir o vínculo sem duplicidades.
B8: Vendedor & Contatos | C8: RECOMENDADO | D8: Texto / Telefone | E8: Nome do representante e telefone/WhatsApp para constar no espelho oficial do pedido.
B9: Tipo de Frete | C9: SIM | D9: CIF / FOB / Retira | E9: CIF: Por conta do fornecedor. FOB: Frete a cobrar/pago pela Mega 12. Retira: Retirada no local.
B10: Condição de Pagamento | C10: SIM | D10: Texto / Prazos | E10: Exemplos: 30/60/90 Dias, Boleto 30 Dias, À Vista. O sistema gera automaticamente o fluxo de duplicatas financeiras.
B11: % OFF / Desconto Comercial | C11: OPCIONAL | D11: Percentual (%) | E11: Percentual de desconto comercial negociado sobre o pedido (ex: 0%, 5%, 10%). O sistema registra no cabeçalho e preserva os preços unitários líquidos da grade.
B12: CÓDIGO FORNECEDOR | C12: SIM | D12: Texto ou Número | E12: Referência do item de acordo com a tabela do fornecedor (ex: 652, REF-1020).
B13: DESCRIÇÃO DO PRODUTO | C13: SIM | D13: Texto Completo | E13: Nome claro do produto, material, dimensões ou modelo.
B14: UNID. | C14: SIM | D14: UN / CX / PCT / PAR / JG | E14: Unidade de medida. Usado no cálculo de conversão e apontamento de avarias de doca.
B15: QTD/CX (Embalagem) | C15: SIM | D15: Número Inteiro | E15: Quantas unidades vêm dentro de cada caixa master ou pacote fechado. (Padrão: 1).
B16: QTD CX (Caixas Solicitadas) | C16: SIM | D16: Número Inteiro | E16: Quantidade de caixas ou fardos comprados.
... B19: Aba SEPARAÇÃO POR LOJA | C19: OPCIONAL | D19: Grade por Filial | E19: Se preenchida, o sistema importa as quantidades exatas por filial. Se deixada em branco, o sistema calcula a divisão automática ideal pelos clusters A/B/C.

Sheet PARAMETROS FISCAIS
B2: PARÂMETROS FISCAIS DE REFERÊNCIA (REDE MEGA 12 - PARANÁ)
B4: PARÂMETRO TRIBUTÁRIO | C4: ALÍQUOTA | D4: DESCRIÇÃO E APLICAÇÃO
B5: ICMS Entrada (Crédito) | C5: 12.0% | D5: Crédito tributário abatido do custo do produto na entrada estadual
B6: Custos Fixos Operacionais | C6: 26.0% | D6: Percentual operacional incidente sobre o PDV nas lojas físicas
B7: ICMS Saída (Alíquota PR) | C7: 19.5% | D7: Alíquota de ICMS sobre a venda final no Estado do Paraná
B8: PIS / COFINS / IR | C8: 6.0% | D8: Impostos federais incidentes sobre o faturamento de saída
B9: IPI Padrão | C9: 0.0% | D9: Imposto sobre Produtos Industrializados (quando aplicável por NCM)
B10: ST (Substituição Tributária) | C10: 0.0% | D10: ICMS-ST destacado por fornecedor (quando aplicável)
